kadoo/config_utils.py
kadoo/entry_utils.py
kadoo/main.py
kadoo/setup_utils.py
kadoo/start_utils.py
kadoo/table_utils.py
kadoo-0.1.6.dist-info/METADATA
kadoo-0.1.6.dist-info/WHEEL
kadoo-0.1.6.dist-info/entry_points.txt
kadoo-0.1.6.dist-info/top_level.txt
kadoo-0.1.6.dist-info/RECORD
