Metadata-Version: 2.1
Name: kadoo
Version: 0.1.6
Summary: The priorities management CLI you never knew you needed
Home-page: https://github.com/TechWiz-3/kadoo-cli
Author: Zac the Wise aka TechWiz-3
Classifier: Development Status :: 5 - Production/Stable
Classifier: Environment :: Console
Classifier: Environment :: Console :: Curses
Classifier: Intended Audience :: Developers
Classifier: Operating System :: Microsoft :: Windows
Classifier: Operating System :: POSIX :: Linux
Classifier: License :: OSI Approved :: GNU General Public License v3 or later (GPLv3+)
Classifier: Programming Language :: Python :: 3
Classifier: Topic :: Utilities
Requires-Dist: rich
Requires-Dist: toml
